odoo/addons/shopfloor_vendor_packaging/README.rst
odoo/addons/shopfloor_vendor_packaging/__init__.py
odoo/addons/shopfloor_vendor_packaging/__manifest__.py
odoo/addons/shopfloor_vendor_packaging/actions/__init__.py
odoo/addons/shopfloor_vendor_packaging/actions/data.py
odoo/addons/shopfloor_vendor_packaging/i18n/it.po
odoo/addons/shopfloor_vendor_packaging/i18n/shopfloor_vendor_packaging.pot
odoo/addons/shopfloor_vendor_packaging/models/__init__.py
odoo/addons/shopfloor_vendor_packaging/models/shopfloor_menu.py
odoo/addons/shopfloor_vendor_packaging/readme/CONTRIBUTORS.rst
odoo/addons/shopfloor_vendor_packaging/readme/DESCRIPTION.rst
odoo/addons/shopfloor_vendor_packaging/static/description/icon.png
odoo/addons/shopfloor_vendor_packaging/static/description/index.html
odoo/addons/shopfloor_vendor_packaging/tests/__init__.py
odoo/addons/shopfloor_vendor_packaging/tests/test_shopfloor_vendor_packaging.py
odoo/addons/shopfloor_vendor_packaging/views/shopfloor_menu.xml
odoo14_addon_shopfloor_vendor_packaging-14.0.1.0.1.dev4.dist-info/METADATA
odoo14_addon_shopfloor_vendor_packaging-14.0.1.0.1.dev4.dist-info/WHEEL
odoo14_addon_shopfloor_vendor_packaging-14.0.1.0.1.dev4.dist-info/top_level.txt
odoo14_addon_shopfloor_vendor_packaging-14.0.1.0.1.dev4.dist-info/RECORD
